megacllib
