Metadata-Version: 1.0
Name: megacl
Version: 0.4.6
Summary: mega.co.nz command line client.
Home-page: https://github.com/gissehel/megacl.git
Author: Arthibus Gisséhel
Author-email: public-dev-megacl@gissehel.org
License: MIT
Keywords: commandline mega.co.nz mega
Platform: UNKNOWN
Classifier: Development Status :: 4 - Beta
Classifier: Environment :: Console
Classifier: Intended Audience :: Information Technology
Classifier: License :: OSI Approved :: MIT License
Classifier: Natural Language :: English
Classifier: Operating System :: OS Independent
Classifier: Programming Language :: Python :: 2
Classifier: Topic :: Communications
Classifier: Topic :: Internet
Classifier: Topic :: System :: Filesystems
Classifier: Topic :: Utilities
